gestion_fechas/__init__.py
gestion_fechas/orquestador.py
gestion_fechas/proceso_etl.py
gestion_fechas/repositorio.py
gestion_fechas/servicio.py
gestion_fechas/utils/excepciones.py
gestion_fechas/utils/fechas_utils.py
gestion_fechas/utils/validador.py
gestion_fechas-5.2.0.dist-info/LICENSE
gestion_fechas-5.2.0.dist-info/METADATA
gestion_fechas-5.2.0.dist-info/WHEEL
gestion_fechas-5.2.0.dist-info/RECORD
