Metadata-Version: 2.1
Name: gestion_fechas
Version: 5.2.0
Summary: Gestión de fechas de las etls python
License: EUPL-1.2
Author: Equipo de integración Valencia smart city
Author-email: integracionvlci@valencia.es
Requires-Python: >=3.12,<4.0
Classifier: License :: OSI Approved :: European Union Public Licence 1.2 (EUPL 1.2)
Classifier: Programming Language :: Python :: 3
Classifier: Programming Language :: Python :: 3.12
Classifier: Programming Language :: Python :: 3.13
Requires-Dist: python-dateutil (>=2.9.0.post0,<3.0.0)
Requires-Dist: pytz (>=2025.2,<2026.0)
Requires-Dist: vlcishared (>=21.0.0,<22.0.0)
